aioqueueext/__init__.py
aioqueueext/base.py
aioqueueext/one_queue.py
aioqueueext/queue.py
aioqueueext/util.py
aioqueueext-0.2.1.dist-info/LICENSE
aioqueueext-0.2.1.dist-info/METADATA
aioqueueext-0.2.1.dist-info/WHEEL
aioqueueext-0.2.1.dist-info/top_level.txt
aioqueueext-0.2.1.dist-info/RECORD
