Metadata-Version: 2.1
Name: aioqueueext
Version: 0.2.1
Summary: Asyncio queues with extended functionality: peeking, setting put and get callbacks.
Author-email: darkhaniop <darkhaniop@google.com>
Project-URL: Homepage, https://github.com/gw-tools/aioqueueext
Project-URL: Bug Tracker, https://github.com/gw-tools/aioqueueext/issues
Keywords: asyncio,queue
Classifier: Intended Audience :: Developers
Classifier: Programming Language :: Python :: 3
Classifier: License :: OSI Approved :: MIT License
Classifier: Operating System :: OS Independent
Classifier: Framework :: AsyncIO
Requires-Python: <4,>=3.7
License-File: LICENSE
